Metadata-Version: 2.1
Name: flower-segmentation-tool
Version: 0.1.6
Summary: A tool to segment yellow arnica flowers in rgb images
Home-page: https://github.com/AnnaTe/arnica
Author: Anna Tenberg
Author-email: Anna.Tenberg@saturn.uni-freiburg.de
License: UNKNOWN
Platform: UNKNOWN
Classifier: Programming Language :: Python :: 3
Classifier: License :: OSI Approved :: GNU General Public License v3 (GPLv3)
Classifier: Operating System :: POSIX :: Linux
Classifier: Topic :: Scientific/Engineering :: Image Recognition
Classifier: Intended Audience :: Science/Research
Requires-Python: >=3.5
Requires-Dist: PyQt5-sip
Requires-Dist: PyQt5
Requires-Dist: numpy
Requires-Dist: opencv-python
Requires-Dist: matplotlib
